[
  {
    "id": 1,
    "tag": "Percentage",
    "q": "A man buys an item for ₹1200 and sells it at a gain of 20%. What is the selling price?",
    "options": ["₹1400", "₹1440", "₹1500", "₹1340"],
    "ans": "B",
    "explain": "Profit = 20% of 1200 = 240. SP = 1200 + 240 = 1440."
  },
  {
    "id": 2,
    "tag": "Time, Speed and Distance",
    "q": "A person crosses a 600m long street in 5 minutes. What is his speed in km/hr?",
    "options": ["3.6", "7.2", "8.4", "10"],
    "ans": "B",
    "explain": "Speed = 2 m/sec = 7.2 km/hr."
  },
  {
    "id": 3,
    "tag": "Simple and Compound Interest",
    "q": "What is the simple interest on ₹1500 at 10% per annum for 2 years?",
    "options": ["₹200", "₹250", "₹300", "₹350"],
    "ans": "C",
    "explain": "SI = (1500 × 10 × 2)/100 = ₹300."
  },
  {
    "id": 4,
    "tag": "Ratio and Proportion",
    "q": "Divide ₹600 in the ratio 2:3.",
    "options": ["₹200, ₹400", "₹240, ₹360", "₹250, ₹350", "₹300, ₹300"],
    "ans": "B",
    "explain": "2/5 of 600 = 240, 3/5 of 600 = 360."
  },
  {
    "id": 14,
    "tag": "Profit & Loss",
    "q": "If cost price is ₹500 and selling price is ₹600, what is the profit percentage?",
    "options": ["10%", "15%", "20%", "25%"],
    "ans": "C",
    "explain": "Profit% = (100/500)*100 = 20%."
  },
  {
    "id": 15,
    "tag": "Averages",
    "q": "Find the average of 10, 20, 30, 40, 50.",
    "options": ["25", "30", "35", "40"],
    "ans": "B",
    "explain": "150/5 = 30."
  },
  {
    "id": 52,
    "tag": "Time & Work",
    "q": "A can do a work in 10 days and B in 15 days. If they work together, in how many days will they finish?",
    "options": ["5", "6", "8", "9"],
    "ans": "B",
    "explain": "Together = (10*15)/(10+15) = 150/25 = 6 days."
  },
  {
    "id": 60,
    "tag": "Divisibility rules",
    "q": "Which of the following is a prime number?",
    "options": ["33", "81", "93", "97"],
    "ans": "D",
    "explain": "97 is a prime number."
  },
  {
    "id": 93,
    "tag": "HCF & LCM",
    "q": "The HCF of two numbers is 11 and their LCM is 693. If one is 77, find the other.",
    "options": ["88", "99", "101", "110"],
    "ans": "B",
    "explain": "(11*693)/77 = 99."
  },
  {
    "id": 101,
    "tag": "Problems on Ages",
    "q": "The sum of ages of 5 children born at intervals of 3 years each is 50 years. Age of the youngest?",
    "options": ["4", "8", "10", "12"],
    "ans": "A",
    "explain": "x + (x+3)... = 50. 5x + 30 = 50. x = 4."
  },
  {
    "id": 105,
    "tag": "Probability",
    "q": "A box has 8 red, 7 blue and 6 green balls. Prob. of picking a blue ball?",
    "options": ["1/3", "1/2", "7/21", "8/21"],
    "ans": "A",
    "explain": "7/21 = 1/3."
  }
]